nogging/__init__.py
nogging-1.1.0.dist-info/LICENSE
nogging-1.1.0.dist-info/METADATA
nogging-1.1.0.dist-info/WHEEL
nogging-1.1.0.dist-info/top_level.txt
nogging-1.1.0.dist-info/RECORD
